demo_greeter_pkg/__init__.py
demo_greeter_pkg/greet.py
demonancyakrimsbdwsjc_pkg-0.1.0.dist-info/licenses/LICENSE
demonancyakrimsbdwsjc_pkg-0.1.0.dist-info/METADATA
demonancyakrimsbdwsjc_pkg-0.1.0.dist-info/WHEEL
demonancyakrimsbdwsjc_pkg-0.1.0.dist-info/entry_points.txt
demonancyakrimsbdwsjc_pkg-0.1.0.dist-info/top_level.txt
demonancyakrimsbdwsjc_pkg-0.1.0.dist-info/RECORD
